{"items":{"p136":{"icon":"58","id":136,"name":"Mac_Scofield","pos":{"x":380,"y":-634},"text":"Health: 98"},"p179":{"icon":"58","id":179,"name":"John_McClain","pos":{"x":376,"y":-637},"text":"Health: 99"},"p198":{"icon":"58","id":198,"name":"Robert_Donahue","pos":{"x":407,"y":-650},"text":"Health: 100"},"p28":{"icon":"58","id":28,"name":"Darien_Alwyn","pos":{"x":277,"y":182},"text":"Health: 50"},"p74":{"icon":"58","id":74,"name":"Rhett_McLaughlin","pos":{"x":375,"y":-633},"text":"Health: 100"},"p85":{"icon":"58","id":85,"name":"Alex_Bodle","pos":{"x":-2000,"y":298},"text":"Health: 62"}}}